fibber/__init__.py
fibber/download_utils.py
fibber/fibber.py
fibber/log.py
fibber/benchmark/__init__.py
fibber/benchmark/benchmark_adversarial_attack.py
fibber/benchmark/benchmark_style_transfer.py
fibber/benchmark/benchmark_utils.py
fibber/benchmark/make_overview.py
fibber/datasets/__init__.py
fibber/datasets/dataset_utils.py
fibber/datasets/download_datasets.py
fibber/datasets/downloadable_datasets.py
fibber/datasets/process_dataset.py
fibber/defense_strategies/__init__.py
fibber/defense_strategies/advtrain_strategy.py
fibber/defense_strategies/defense_strategy_base.py
fibber/defense_strategies/lmag_strategy.py
fibber/defense_strategies/sapd_strategy.py
fibber/defense_strategies/sem_strategy.py
fibber/metrics/__init__.py
fibber/metrics/attack_aggregation_utils.py
fibber/metrics/bert_lm_utils.py
fibber/metrics/metric_base.py
fibber/metrics/metric_utils.py
fibber/metrics/classifier/__init__.py
fibber/metrics/classifier/classifier_base.py
fibber/metrics/classifier/fasttext_classifier.py
fibber/metrics/classifier/input_manipulation_classifier.py
fibber/metrics/classifier/shield_classifier.py
fibber/metrics/classifier/transformer_classifier.py
fibber/metrics/distance/__init__.py
fibber/metrics/distance/edit_distance_metric.py
fibber/metrics/distance/ref_bleu_metric.py
fibber/metrics/distance/self_bleu_metric.py
fibber/metrics/fluency/__init__.py
fibber/metrics/fluency/bert_perplexity_metric.py
fibber/metrics/fluency/gpt2_perplexity_metric.py
fibber/metrics/similarity/__init__.py
fibber/metrics/similarity/ce_similarity_metric.py
fibber/metrics/similarity/glove_similarity_metric.py
fibber/metrics/similarity/use_similarity_metric.py
fibber/paraphrase_strategies/__init__.py
fibber/paraphrase_strategies/asrs_strategy.py
fibber/paraphrase_strategies/asrs_utils_wpe.py
fibber/paraphrase_strategies/cheat_strategy.py
fibber/paraphrase_strategies/fudge_strategy.py
fibber/paraphrase_strategies/identity_strategy.py
fibber/paraphrase_strategies/openattack_strategy.py
fibber-0.4.0.dist-info/AUTHORS.rst
fibber-0.4.0.dist-info/LICENSE
fibber-0.4.0.dist-info/METADATA
fibber-0.4.0.dist-info/WHEEL
fibber-0.4.0.dist-info/top_level.txt
fibber-0.4.0.dist-info/RECORD
