Metadata-Version: 2.1
Name: fibber
Version: 0.4.0
Summary: Fibber is a benchmarking suite for adversarial attacks on text classification.
Home-page: https://github.com/DAI-Lab/fibber
Author: MIT Data To AI Lab
Author-email: dailabmit@gmail.com
License: MIT license
Keywords: fibber fibber fibber
Platform: UNKNOWN
Classifier: Development Status :: 2 - Pre-Alpha
Classifier: Intended Audience :: Developers
Classifier: License :: OSI Approved :: MIT License
Classifier: Natural Language :: English
Classifier: Programming Language :: Python :: 3
Classifier: Programming Language :: Python :: 3.6
Classifier: Programming Language :: Python :: 3.7
Classifier: Programming Language :: Python :: 3.8
Requires-Python: >=3.6
Requires-Dist: numpy (>=1.18.0)
Requires-Dist: tensorflow-gpu (>=2.0.0)
Requires-Dist: tensorflow-hub (>=0.9.0)
Requires-Dist: torch (<2,>=1.0)
Requires-Dist: torchvision (<1,>=0.4.2)
Requires-Dist: transformers (>=2.4.0)
Requires-Dist: tqdm (>=4.0.0)
Requires-Dist: spacy (>=2.0.0)
Requires-Dist: pandas (>=1.0.0)
Requires-Dist: nltk (>=3.0)
Requires-Dist: rake-nltk (>=1.0.4)
Requires-Dist: stanza (>=1.1.0)
Requires-Dist: sentence-transformers (>=0.3.0)
Requires-Dist: fasttext (>=0.9.0)
Requires-Dist: expiringdict (>=1.2.0)
Provides-Extra: dev
Requires-Dist: bumpversion (>=0.5.3) ; extra == 'dev'
Requires-Dist: pip (>=9.0.1) ; extra == 'dev'
Requires-Dist: watchdog (>=0.8.3) ; extra == 'dev'
Requires-Dist: m2r2 (<0.3,>=0.2.5) ; extra == 'dev'
Requires-Dist: nbsphinx (<0.7,>=0.5.0) ; extra == 'dev'
Requires-Dist: Sphinx (==3.2.1) ; extra == 'dev'
Requires-Dist: pydata-sphinx-theme ; extra == 'dev'
Requires-Dist: autodocsumm (>=0.1.10) ; extra == 'dev'
Requires-Dist: PyYaml (<6,>=5.3.1) ; extra == 'dev'
Requires-Dist: argh (<1,>=0.26.2) ; extra == 'dev'
Requires-Dist: sphinx-rtd-theme (<1,>=0.4) ; extra == 'dev'
Requires-Dist: ipython (<8,>=7) ; extra == 'dev'
Requires-Dist: flake8 (>=3.7.7) ; extra == 'dev'
Requires-Dist: isort (>=5) ; extra == 'dev'
Requires-Dist: autoflake (>=1.2) ; extra == 'dev'
Requires-Dist: autopep8 (>=1.4.3) ; extra == 'dev'
Requires-Dist: twine (>=1.10.0) ; extra == 'dev'
Requires-Dist: wheel (>=0.30.0) ; extra == 'dev'
Requires-Dist: coverage (>=4.5.1) ; extra == 'dev'
Requires-Dist: tox (>=2.9.1) ; extra == 'dev'
Requires-Dist: pytest (>=3.4.2) ; extra == 'dev'
Requires-Dist: pytest-cov (>=2.6.0) ; extra == 'dev'
Provides-Extra: test
Requires-Dist: pytest (>=3.4.2) ; extra == 'test'
Requires-Dist: pytest-cov (>=2.6.0) ; extra == 'test'
